odoo/addons/sale_margin_delivered/README.rst
odoo/addons/sale_margin_delivered/__init__.py
odoo/addons/sale_margin_delivered/__manifest__.py
odoo/addons/sale_margin_delivered/i18n/es.po
odoo/addons/sale_margin_delivered/i18n/it.po
odoo/addons/sale_margin_delivered/i18n/sale_margin_delivered.pot
odoo/addons/sale_margin_delivered/models/__init__.py
odoo/addons/sale_margin_delivered/models/sale_margin.py
odoo/addons/sale_margin_delivered/readme/CONFIGURE.md
odoo/addons/sale_margin_delivered/readme/CONTEXT.md
odoo/addons/sale_margin_delivered/readme/CONTRIBUTORS.md
odoo/addons/sale_margin_delivered/readme/DESCRIPTION.md
odoo/addons/sale_margin_delivered/readme/USAGE.md
odoo/addons/sale_margin_delivered/reports/__init__.py
odoo/addons/sale_margin_delivered/reports/sale_report.py
odoo/addons/sale_margin_delivered/static/description/icon.png
odoo/addons/sale_margin_delivered/static/description/index.html
odoo/addons/sale_margin_delivered/tests/__init__.py
odoo/addons/sale_margin_delivered/tests/test_sale_margin_delivered.py
odoo/addons/sale_margin_delivered/views/sale_margin_delivered_view.xml
odoo_addon_sale_margin_delivered-18.0.1.0.0.3.dist-info/METADATA
odoo_addon_sale_margin_delivered-18.0.1.0.0.3.dist-info/WHEEL
odoo_addon_sale_margin_delivered-18.0.1.0.0.3.dist-info/top_level.txt
odoo_addon_sale_margin_delivered-18.0.1.0.0.3.dist-info/RECORD
